{
  "update_time": "2026-06-07 02:08:52",
  "date": "2026-06-07",
  "total": 13,
  "sources": {
    "資策會": 5,
    "工研院": 8
  },
  "data": [
    {
      "來源": "資策會",
      "案號": "123",
      "標題": "2",
      "標題連結": "https://bid.iii.org.tw/bid/list/bid_new_list.aspx?bid_no=123",
      "預算金額": "",
      "公告日": "-",
      "截止日": "-",
      "狀態": "1",
      "採購類型": "",
      "採購方式": "",
      "公佈日": "",
      "投標日": "",
      "開標日": "",
      "查詢日期": "",
      "招標狀態": "",
      "更正日期": ""
    },
    {
      "來源": "工研院",
      "案號": "A012000485",
      "標題": "光復院區廢水場污泥脫水及清理作業",
      "標題連結": "https://vendor.itri.org.tw/broadBdetail2.aspx?seq=1E409887-A9A2-488A-AD77-0ABF6524BF39",
      "預算金額": "",
      "公告日": "115/06/05",
      "截止日": "115/06/16",
      "狀態": "P",
      "採購類型": "",
      "採購方式": "",
      "公佈日": "",
      "投標日": "",
      "開標日": "",
      "查詢日期": "",
      "招標狀態": "",
      "更正日期": ""
    },
    {
      "來源": "工研院",
      "案號": "A012000492",
      "標題": "光明新村140號日照中心整修工程（詳採購規範書）",
      "標題連結": "https://vendor.itri.org.tw/broadBdetail2.aspx?seq=F07F844C-8CDB-4C13-AA01-3771F85004C9",
      "預算金額": "",
      "公告日": "115/06/05",
      "截止日": "115/06/22",
      "狀態": "P",
      "採購類型": "",
      "採購方式": "",
      "公佈日": "",
      "投標日": "",
      "開標日": "",
      "查詢日期": "",
      "招標狀態": "",
      "更正日期": ""
    },
    {
      "來源": "工研院",
      "案號": "A512002571",
      "標題": "ANSYS Maxwell套裝軟體使用授權",
      "標題連結": "https://vendor.itri.org.tw/broadBdetail2.aspx?seq=F0803249-D29A-49BA-B616-40B9295108A6",
      "預算金額": "",
      "公告日": "115/06/05",
      "截止日": "115/06/15",
      "狀態": "P",
      "採購類型": "",
      "採購方式": "",
      "公佈日": "",
      "投標日": "",
      "開標日": "",
      "查詢日期": "",
      "招標狀態": "",
      "更正日期": ""
    },
    {
      "來源": "工研院",
      "案號": "A522000956",
      "標題": "防詐情資AI分析與處理(平台資訊爬蟲與詐騙風險智能處理)",
      "標題連結": "https://vendor.itri.org.tw/broadBdetail2.aspx?seq=1C9CBFED-E22E-48B5-A8C2-C22FBA5F63C6",
      "預算金額": "",
      "公告日": "115/06/05",
      "截止日": "115/06/22",
      "狀態": "P",
      "採購類型": "",
      "採購方式": "",
      "公佈日": "",
      "投標日": "",
      "開標日": "",
      "查詢日期": "",
      "招標狀態": "",
      "更正日期": ""
    },
    {
      "來源": "工研院",
      "案號": "A522000958",
      "標題": "網詐網雲端主機租用與資訊安全檢測監控相關服務",
      "標題連結": "https://vendor.itri.org.tw/broadBdetail2.aspx?seq=C3A6794F-BB35-4DB2-B6AA-9565A3BBBC98",
      "預算金額": "",
      "公告日": "115/06/05",
      "截止日": "115/06/22",
      "狀態": "P",
      "採購類型": "",
      "採購方式": "",
      "公佈日": "",
      "投標日": "",
      "開標日": "",
      "查詢日期": "",
      "招標狀態": "",
      "更正日期": ""
    },
    {
      "來源": "工研院",
      "案號": "A522000959",
      "標題": "資訊設備租金及網路安全及資安維運相關服務(資訊設備租金)",
      "標題連結": "https://vendor.itri.org.tw/broadBdetail2.aspx?seq=F1DECF0F-6E74-4FC8-BB6B-73F670351C3D",
      "預算金額": "",
      "公告日": "115/06/05",
      "截止日": "115/06/22",
      "狀態": "P",
      "採購類型": "",
      "採購方式": "",
      "公佈日": "",
      "投標日": "",
      "開標日": "",
      "查詢日期": "",
      "招標狀態": "",
      "更正日期": ""
    },
    {
      "來源": "工研院",
      "案號": "A522000970",
      "標題": "網路詐騙通報查詢網站跨部會審查與外部子系統施作、維護與防詐情資交換",
      "標題連結": "https://vendor.itri.org.tw/broadBdetail2.aspx?seq=A3915276-C9B4-47C8-BE0D-A9081BEB9A9A",
      "預算金額": "",
      "公告日": "115/06/05",
      "截止日": "115/06/22",
      "狀態": "P",
      "採購類型": "",
      "採購方式": "",
      "公佈日": "",
      "投標日": "",
      "開標日": "",
      "查詢日期": "",
      "招標狀態": "",
      "更正日期": ""
    },
    {
      "來源": "工研院",
      "案號": "A542003373",
      "標題": "光復院區6館17館空調管路汰舊更新作業",
      "標題連結": "https://vendor.itri.org.tw/broadBdetail2.aspx?seq=39738AC2-26B7-440C-84FC-56D02A8A11B9",
      "預算金額": "",
      "公告日": "115/06/05",
      "截止日": "115/06/17",
      "狀態": "P",
      "採購類型": "",
      "採購方式": "",
      "公佈日": "",
      "投標日": "",
      "開標日": "",
      "查詢日期": "",
      "招標狀態": "",
      "更正日期": ""
    },
    {
      "來源": "資策會",
      "案號": "PP26020076",
      "標題": "「智慧杆資料應用整合工作坊徵集」採購案",
      "標題連結": "https://bid.iii.org.tw/bid/list/bid_new_list.aspx?bid_no=PP26020076",
      "預算金額": "1300000",
      "公告日": "115/06/07",
      "截止日": "115/03/17",
      "狀態": "公告中",
      "採購類型": "",
      "採購方式": "",
      "公佈日": "",
      "投標日": "",
      "開標日": "",
      "查詢日期": "",
      "招標狀態": "",
      "更正日期": ""
    },
    {
      "來源": "資策會",
      "案號": "PP26060004",
      "標題": "「居家關懷服務驗證支援與宣導推廣」採購案",
      "標題連結": "https://bid.iii.org.tw/bid/list/bid_new_list.aspx?bid_no=PP26060004&ord=1",
      "預算金額": "500000",
      "公告日": "115/06/05",
      "截止日": "115/06/11",
      "狀態": "第1次",
      "採購類型": "",
      "採購方式": "",
      "公佈日": "",
      "投標日": "",
      "開標日": "",
      "查詢日期": "",
      "招標狀態": "",
      "更正日期": ""
    },
    {
      "來源": "資策會",
      "案號": "PP26060034",
      "標題": "「公益主題AI解決方案產業擴展推動與執行」採購案",
      "標題連結": "https://bid.iii.org.tw/bid/list/bid_new_list.aspx?bid_no=PP26060034&ord=1",
      "預算金額": "1400000",
      "公告日": "115/06/05",
      "截止日": "115/06/09",
      "狀態": "第1次",
      "採購類型": "",
      "採購方式": "",
      "公佈日": "",
      "投標日": "",
      "開標日": "",
      "查詢日期": "",
      "招標狀態": "",
      "更正日期": ""
    },
    {
      "來源": "資策會",
      "案號": "PP26060036",
      "標題": "「科技大樓8樓自設箱型冷氣主機更換」採購案",
      "標題連結": "https://bid.iii.org.tw/bid/list/bid_new_list.aspx?bid_no=PP26060036&ord=1",
      "預算金額": "348600",
      "公告日": "115/06/05",
      "截止日": "115/06/17",
      "狀態": "第1次",
      "採購類型": "",
      "採購方式": "",
      "公佈日": "",
      "投標日": "",
      "開標日": "",
      "查詢日期": "",
      "招標狀態": "",
      "更正日期": ""
    }
  ]
}