{
  "date": "2026-07-19",
  "attempt": 7,
  "sources": {
    "工研院": {
      "status": "ok",
      "count": 16,
      "time": "10:56:31",
      "error": ""
    },
    "資策會": {
      "status": "ok",
      "count": 11,
      "time": "10:56:46",
      "error": ""
    },
    "中研院": {
      "status": "ok",
      "count": 0,
      "time": "10:56:50",
      "error": ""
    }
  },
  "logs": [
    {
      "time": "01:07:15",
      "msg": "工研院：成功，16 筆"
    },
    {
      "time": "01:07:32",
      "msg": "資策會：成功，11 筆"
    },
    {
      "time": "01:07:36",
      "msg": "中研院：目前無新標案"
    },
    {
      "time": "03:08:20",
      "msg": "工研院：成功，16 筆"
    },
    {
      "time": "03:08:37",
      "msg": "資策會：成功，11 筆"
    },
    {
      "time": "03:08:41",
      "msg": "中研院：目前無新標案"
    },
    {
      "time": "04:51:57",
      "msg": "工研院：成功，16 筆"
    },
    {
      "time": "04:52:13",
      "msg": "資策會：成功，11 筆"
    },
    {
      "time": "04:52:17",
      "msg": "中研院：目前無新標案"
    },
    {
      "time": "05:53:08",
      "msg": "工研院：成功，16 筆"
    },
    {
      "time": "05:53:25",
      "msg": "資策會：成功，11 筆"
    },
    {
      "time": "05:53:29",
      "msg": "中研院：目前無新標案"
    },
    {
      "time": "06:52:24",
      "msg": "工研院：成功，16 筆"
    },
    {
      "time": "06:52:37",
      "msg": "資策會：成功，11 筆"
    },
    {
      "time": "06:52:40",
      "msg": "中研院：目前無新標案"
    },
    {
      "time": "07:55:32",
      "msg": "工研院：成功，16 筆"
    },
    {
      "time": "07:55:48",
      "msg": "資策會：成功，11 筆"
    },
    {
      "time": "07:55:52",
      "msg": "中研院：目前無新標案"
    },
    {
      "time": "10:56:31",
      "msg": "工研院：成功，16 筆"
    },
    {
      "time": "10:56:46",
      "msg": "資策會：成功，11 筆"
    },
    {
      "time": "10:56:50",
      "msg": "中研院：目前無新標案"
    }
  ]
}