{
  "date": "2026-07-13",
  "attempt": 1,
  "sources": {
    "工研院": {
      "status": "ok",
      "count": 17,
      "time": "00:04:49",
      "error": ""
    },
    "資策會": {
      "status": "ok",
      "count": 12,
      "time": "00:05:06",
      "error": ""
    },
    "中研院": {
      "status": "ok",
      "count": 0,
      "time": "00:05:09",
      "error": ""
    }
  },
  "logs": [
    {
      "time": "00:04:49",
      "msg": "工研院：成功，17 筆"
    },
    {
      "time": "00:05:06",
      "msg": "資策會：成功，12 筆"
    },
    {
      "time": "00:05:09",
      "msg": "中研院：目前無新標案"
    }
  ]
}