{
  "date": "2026-04-22",
  "attempt": 2,
  "sources": {
    "工研院": {
      "status": "ok",
      "count": 20,
      "time": "03:17:06",
      "error": ""
    },
    "資策會": {
      "status": "ok",
      "count": 10,
      "time": "03:17:29",
      "error": ""
    },
    "中研院": {
      "status": "ok",
      "count": 0,
      "time": "03:17:32",
      "error": ""
    }
  },
  "logs": [
    {
      "time": "01:06:14",
      "msg": "工研院：成功，20 筆"
    },
    {
      "time": "01:06:30",
      "msg": "資策會：成功，10 筆"
    },
    {
      "time": "01:06:34",
      "msg": "中研院：目前無新標案"
    },
    {
      "time": "03:17:06",
      "msg": "工研院：成功，20 筆"
    },
    {
      "time": "03:17:29",
      "msg": "資策會：成功，10 筆"
    },
    {
      "time": "03:17:32",
      "msg": "中研院：目前無新標案"
    }
  ]
}